cli.py
rabisco.py
rabisco-0.2.0.dist-info/METADATA
rabisco-0.2.0.dist-info/RECORD
rabisco-0.2.0.dist-info/WHEEL
rabisco-0.2.0.dist-info/entry_points.txt
rabisco-0.2.0.dist-info/top_level.txt
