Metadata-Version: 2.1
Name: rabisco
Version: 0.2.0
Summary: note cli app
Home-page: https://github.com/rougeth/rabisco
Author: Marco Rougeth
Author-email: marco@rougeth.com
License: UNKNOWN
Platform: UNKNOWN
Requires-Dist: click
Requires-Dist: python-slugify
